dimredpy/JaxLDA.py
dimredpy/JaxPCA.py
dimredpy/JaxRPCA.py
dimredpy/__init__.py
dimredpy-1.0.2.dist-info/LICENSE
dimredpy-1.0.2.dist-info/METADATA
dimredpy-1.0.2.dist-info/WHEEL
dimredpy-1.0.2.dist-info/RECORD
